mle_hyperopt/__init__.py
mle_hyperopt/_version.py
mle_hyperopt/cli.py
mle_hyperopt/decorator.py
mle_hyperopt/space.py
mle_hyperopt/strategy.py
mle_hyperopt/spaces/__init__.py
mle_hyperopt/spaces/grid.py
mle_hyperopt/spaces/nevergrad.py
mle_hyperopt/spaces/random.py
mle_hyperopt/spaces/smbo.py
mle_hyperopt/strategies/__init__.py
mle_hyperopt/strategies/coordinate.py
mle_hyperopt/strategies/grid.py
mle_hyperopt/strategies/halving.py
mle_hyperopt/strategies/hyperband.py
mle_hyperopt/strategies/nevergrad.py
mle_hyperopt/strategies/random.py
mle_hyperopt/strategies/smbo.py
mle_hyperopt/strategies/pbt/__init__.py
mle_hyperopt/strategies/pbt/exploit.py
mle_hyperopt/strategies/pbt/explore.py
mle_hyperopt/strategies/pbt/pbt.py
mle_hyperopt/utils/__init__.py
mle_hyperopt/utils/comms.py
mle_hyperopt/utils/helpers.py
mle_hyperopt/utils/plotting.py
mle_hyperopt-0.0.10.dist-info/LICENSE
mle_hyperopt-0.0.10.dist-info/METADATA
mle_hyperopt-0.0.10.dist-info/WHEEL
mle_hyperopt-0.0.10.dist-info/entry_points.txt
mle_hyperopt-0.0.10.dist-info/top_level.txt
mle_hyperopt-0.0.10.dist-info/RECORD
