Metadata-Version: 2.1
Name: mle_hyperopt
Version: 0.0.10
Summary: Machine Learning Experiment Hyperparameter Optimization
Home-page: https://github.com/mle-infrastructure/mle-hyperopt
Download-URL: https://github.com/mle-infrastructure/mle-hyperopt/archive/v0.0.10.tar.gz
Author: Robert Tjarko Lange
Author-email: robertlange0@gmail.com
Platform: any
Classifier: Programming Language :: Python :: 3.6
Classifier: Programming Language :: Python :: 3.7
Classifier: Programming Language :: Python :: 3.8
Classifier: Programming Language :: Python :: 3.9
Classifier: License :: OSI Approved :: MIT License
Classifier: Operating System :: OS Independent
Classifier: Topic :: Scientific/Engineering :: Artificial Intelligence
Requires-Python: >=3.6
License-File: LICENSE
Requires-Dist: numpy
Requires-Dist: pandas
Requires-Dist: rich
Requires-Dist: dotmap
Requires-Dist: pyyaml>=5.1
Requires-Dist: pickle5; python_version < "3.8"
Provides-Extra: examples
Requires-Dist: torch; extra == "examples"
Requires-Dist: nevergrad; extra == "examples"
Requires-Dist: scikit-optimize; extra == "examples"
Requires-Dist: scikit-learn==0.24.2; extra == "examples"
Requires-Dist: matplotlib; extra == "examples"
Requires-Dist: seaborn; extra == "examples"
Requires-Dist: mle-scheduler; extra == "examples"
Requires-Dist: mle-logging; extra == "examples"
Provides-Extra: full
Requires-Dist: nevergrad; extra == "full"
Requires-Dist: scikit-optimize; extra == "full"
Requires-Dist: matplotlib; extra == "full"
Requires-Dist: seaborn; extra == "full"
